open_ticket_ai/__init__.py
open_ticket_ai/app.py
open_ticket_ai/main.py
open_ticket_ai/core/AGENTS.md
open_ticket_ai/core/__init__.py
open_ticket_ai/core/base_model.py
open_ticket_ai/core/_util/__init__.py
open_ticket_ai/core/_util/formatting.py
open_ticket_ai/core/_util/hashes.py
open_ticket_ai/core/ai_classification_services/__init__.py
open_ticket_ai/core/ai_classification_services/classification_models.py
open_ticket_ai/core/ai_classification_services/classification_service.py
open_ticket_ai/core/config/__init__.py
open_ticket_ai/core/config/app_config.py
open_ticket_ai/core/config/config_builder.py
open_ticket_ai/core/config/config_models.py
open_ticket_ai/core/config/errors.py
open_ticket_ai/core/config/pipe_config_builder.py
open_ticket_ai/core/config/types.py
open_ticket_ai/core/config/templates/__init__.py
open_ticket_ai/core/dependency_injection/__init__.py
open_ticket_ai/core/dependency_injection/component_registry.py
open_ticket_ai/core/dependency_injection/container.py
open_ticket_ai/core/dependency_injection/service_registry_util.py
open_ticket_ai/core/injectables/__init__.py
open_ticket_ai/core/injectables/injectable.py
open_ticket_ai/core/injectables/injectable_models.py
open_ticket_ai/core/logging/__init__.py
open_ticket_ai/core/logging/logging_iface.py
open_ticket_ai/core/logging/logging_models.py
open_ticket_ai/core/logging/stdlib_logging_adapter.py
open_ticket_ai/core/pipes/__init__.py
open_ticket_ai/core/pipes/pipe.py
open_ticket_ai/core/pipes/pipe_context_model.py
open_ticket_ai/core/pipes/pipe_factory.py
open_ticket_ai/core/pipes/pipe_models.py
open_ticket_ai/core/plugins/__init__.py
open_ticket_ai/core/plugins/plugin.py
open_ticket_ai/core/plugins/plugin_loader.py
open_ticket_ai/core/template_rendering/__init__.py
open_ticket_ai/core/template_rendering/template_renderer.py
open_ticket_ai/core/ticket_system_integration/__init__.py
open_ticket_ai/core/ticket_system_integration/ticket_system_service.py
open_ticket_ai-1.5.14.dist-info/licenses/LICENSE
open_ticket_ai-1.5.14.dist-info/METADATA
open_ticket_ai-1.5.14.dist-info/WHEEL
open_ticket_ai-1.5.14.dist-info/entry_points.txt
open_ticket_ai-1.5.14.dist-info/top_level.txt
open_ticket_ai-1.5.14.dist-info/RECORD
