Metadata-Version: 2.4
Name: open_ticket_ai
Version: 1.5.14
Summary: AI-powered ticket processing and automation system
Author-email: Tobias Bück <tab@softoft.de>
License-Expression: LGPL-2.1-only
Project-URL: Homepage, https://open-ticket-ai.com
Project-URL: Repository, https://github.com/Softoft-Orga/open-ticket-ai
Project-URL: Documentation, https://open-ticket-ai.com
Keywords: ai,ticket-system,automation,nlp,workflow
Classifier: Development Status :: 4 - Beta
Classifier: Intended Audience :: Developers
Classifier: Intended Audience :: Information Technology
Classifier: Intended Audience :: System Administrators
Classifier: Operating System :: OS Independent
Classifier: Programming Language :: Python :: 3
Classifier: Programming Language :: Python :: 3.14
Classifier: Topic :: Software Development :: Libraries :: Python Modules
Classifier: Topic :: Office/Business
Classifier: Topic :: Scientific/Engineering :: Artificial Intelligence
Requires-Python: >=3.14
License-File: LICENSE
Requires-Dist: pydantic~=2.12.0
Requires-Dist: pyyaml~=6.0.0
Requires-Dist: pyfiglet~=1.0.2
Requires-Dist: apscheduler~=3.11.0
Requires-Dist: jinja2~=3.1.6
Requires-Dist: transformers~=4.57.1
Requires-Dist: python-dotenv~=1.1.1
Requires-Dist: typer~=0.19.2
Requires-Dist: rich~=14.2.0
Requires-Dist: httpx~=0.27.0
Requires-Dist: otobo-znuny~=1.4.0
Requires-Dist: pydantic-settings>=2.11.0
Requires-Dist: tabulate>=0.9.0
Requires-Dist: types-tabulate>=0.9.0.20241207
Requires-Dist: pytest-cov>=6.0.0
Requires-Dist: injector>=0.22.0
Requires-Dist: otai-hf-local
Requires-Dist: otai-otobo-znuny
Requires-Dist: otai-zammad
Requires-Dist: otai-base
Requires-Dist: huggingface-hub[hf-xet]>=0.35.3
Requires-Dist: pydeps>=3.0.1
Requires-Dist: graphviz>=0.21
Requires-Dist: async-lru>=2.0.5
Requires-Dist: setuptools-scm>=9.2.2
Requires-Dist: pydantic-extra-types[pendulum]>=2.10.6
Requires-Dist: node-semver>=0.9.0
Requires-Dist: semver>=3.0.4
Dynamic: license-file
